[
  {
    "user": "Roy D",
    "content": "Apollo 11 blasts off from Launch Pad 39A at Cape Kennedy",
    "timestamp": "2021-10-02 20:49:02",
    "tags": [
      "apollo 11",
      "launch"
    ]
  },
  {
    "user": "Jasper W",
    "content": "Spacecraft is reported 22,000 nautical miles from Earth and traveling at 12,914 feet per second",
    "timestamp": "2021-10-02 21:49:52",
    "tags": [
      "spacecraft"
    ]
  },
  {
    "user": "Roy D",
    "content": "Bolt 1 released, 12.5 turns to release",
    "timestamp": "2021-10-03 11:56:10",
    "tags": [
      "landing gear",
      "rover"
    ]
  },
  {
    "user": "Manchu Y",
    "content": "Critical loss of signal to intermediary satellite, connection regained after 5.05 seconds",
    "timestamp": "2021-10-03 11:57:22",
    "tags": [
      "communications",
      "satellite"
    ]
  },
  {
    "user": "Julia M",
    "content": "Flight controller 3 reaching 75.6 degrees (warning zone)",
    "timestamp": "2021-10-03 14:48:18",
    "tags": [
      "flight controller",
      "warning"
    ]
  },
  {
    "user": "Niklas B",
    "content": "(Critical) Radio Failed",
    "timestamp": "2021-10-03 15:11:26",
    "tags": [
      "communications",
      "critical"
    ]
  },
  {
    "user": "Nathan L",
    "content": "The spacecraft is 37 nautical miles high, downrange 61 nautical miles and traveling at 9,300 feet per second or about 6,340 miles per hour",
    "timestamp": "2021-10-03 15:32:02",
    "tags": [
      "spacecraft"
    ]
  }
]